selenium_peacemaker/__init__.py
selenium_peacemaker/__profile__.py
selenium_peacemaker/__proxy__.py
selenium_peacemaker-1.0.0.dist-info/LICENSE.md
selenium_peacemaker-1.0.0.dist-info/METADATA
selenium_peacemaker-1.0.0.dist-info/WHEEL
selenium_peacemaker-1.0.0.dist-info/top_level.txt
selenium_peacemaker-1.0.0.dist-info/RECORD
