Metadata-Version: 2.1
Name: selenium-peacemaker
Version: 1.0.0
Summary: Stealth emulate and automate Chrome using profiles, proxy and selenium.
Home-page: https://github.com/hacknapier/selenium_peacemaker
Author: Hack Napier
Author-email: hacknapier@aol.com
Project-URL: Documentation, https://github.com/hacknapier/selenium_peacemaker
Project-URL: Bug Reports, https://github.com/hacknapier/selenium_peacemaker/issues
Project-URL: Source Code, https://github.com/hacknapier/selenium_peacemaker
Keywords: Selenium,emulation,automation,undetected-chromedriver,webautomation,selenium-stealth,selenium-android,anti-bot-detection
Classifier: Development Status :: 2 - Pre-Alpha
Classifier: Intended Audience :: Developers
Classifier: Programming Language :: Python :: 3
Classifier: Programming Language :: Python :: 3.7
Classifier: Programming Language :: Python :: 3.8
Classifier: Programming Language :: Python :: 3.9
Classifier: Programming Language :: Python :: 3.10
Classifier: Programming Language :: Python :: 3.11
Classifier: License :: Free for non-commercial use
Classifier: Natural Language :: English
Classifier: Operating System :: Microsoft :: Windows
Classifier: Framework :: Jupyter
Classifier: Topic :: Internet
Classifier: Topic :: Internet :: WWW/HTTP :: Browsers
Requires-Python: >=3.7
License-File: LICENSE.md
Requires-Dist: selenium (~=4.6)
Requires-Dist: requests (~=2.28)
Requires-Dist: selenium-interceptor (>=1.0.2)
Requires-Dist: selenium-profiles (==2.2.5.1)
Requires-Dist: selenium-stealth (==1.0.6)
Requires-Dist: undetected-chromedriver (==3.2.1)
Provides-Extra: dev
Requires-Dist: check-manifest ; extra == 'dev'
